AMPyGameLib/__init__.py
AMPyGameLib/ampgl.py
ampgl-0.0.1.dist-info/METADATA
ampgl-0.0.1.dist-info/WHEEL
ampgl-0.0.1.dist-info/top_level.txt
ampgl-0.0.1.dist-info/RECORD
