Metadata-Version: 2.1
Name: ampgl
Version: 0.0.1
Summary: Pygame library with a lot of useful utilities.
Home-page: https://github.com
Author: loggys-MetsA
Author-email: albertmetsler3008@gmail.com
License: UNKNOWN
Project-URL: GitHub, https://github.com/LoggysGit
Keywords: ampgl games am pgl
Platform: UNKNOWN
Classifier: Programming Language :: Python :: 3.9
Classifier: License :: OSI Approved :: MIT License
Classifier: Operating System :: OS Independent
Requires-Python: >=3.6
Requires-Dist: requests>=2.25.1
